nl2sql/__init__.py
nl2sql/core/__init__.py
nl2sql/core/database.py
nl2sql/core/nl2sql.py
nl2sql/llm_providers/__init__.py
nl2sql/llm_providers/anthropic_provider.py
nl2sql/llm_providers/base.py
nl2sql/llm_providers/cohere_provider.py
nl2sql/llm_providers/openai_provider.py
nl2sql/utils/__init__.py
nl2sql/utils/query_validator.py
nl2sql/utils/schema_analyzer.py
nl2sql_py-0.1.0.dist-info/METADATA
nl2sql_py-0.1.0.dist-info/WHEEL
nl2sql_py-0.1.0.dist-info/top_level.txt
nl2sql_py-0.1.0.dist-info/RECORD
