Metadata-Version: 2.1
Name: nl2sql-py
Version: 0.1.0
Summary: Convert natural language to SQL queries using LLMs
Home-page: https://github.com/MohamedElghobary/nl2sql
Author: Mohamed Abdeltawab
Author-email: m.abdeltawab.elghobary@gmail.com
Classifier: Development Status :: 3 - Alpha
Classifier: Intended Audience :: Developers
Classifier: License :: OSI Approved :: MIT License
Classifier: Operating System :: OS Independent
Classifier: Programming Language :: Python :: 3
Classifier: Programming Language :: Python :: 3.8
Classifier: Programming Language :: Python :: 3.9
Classifier: Programming Language :: Python :: 3.10
Classifier: Programming Language :: Python :: 3.11
Requires-Python: >=3.8
Requires-Dist: sqlalchemy>=2.0.0
Requires-Dist: pandas>=1.3.0
Requires-Dist: python-dotenv>=0.19.0
Requires-Dist: openai>=1.0.0
Requires-Dist: cohere>=4.0.0
Requires-Dist: anthropic>=0.25.0
Requires-Dist: psycopg2-binary>=2.9.0
Requires-Dist: mysql-connector-python>=8.0.0
Requires-Dist: pymongo>=4.0.0
Requires-Dist: pytest>=7.0.0
Requires-Dist: black>=22.0.0
Requires-Dist: flake8>=4.0.0
Provides-Extra: dev
Requires-Dist: pytest>=7.0; extra == "dev"
Requires-Dist: black>=22.0; extra == "dev"
Requires-Dist: flake8>=4.0; extra == "dev"
Requires-Dist: mypy>=0.950; extra == "dev"
